README.md
setup.cfg
setup.py
dsnd_distributions140597/Binomialdistribution.py
dsnd_distributions140597/Gaussiandistribution.py
dsnd_distributions140597/Generaldistribution.py
dsnd_distributions140597/__init__.py
dsnd_distributions140597.egg-info/PKG-INFO
dsnd_distributions140597.egg-info/SOURCES.txt
dsnd_distributions140597.egg-info/dependency_links.txt
dsnd_distributions140597.egg-info/not-zip-safe
dsnd_distributions140597.egg-info/top_level.txt