Metadata-Version: 1.0
Name: dsnd-distributions140597
Version: 0.1
Summary: Gaussian and Binomial distributions
Home-page: UNKNOWN
Author: Kimebmen Simbolon
Author-email: kimebmen14@gmail.com
License: UNKNOWN
Platform: UNKNOWN
